mpesa_payments/__init__.py
mpesa_payments/mpesa_payments.py
mpesa_payments/testing.py
mpesa_payments-1.0.1.dist-info/License.txt
mpesa_payments-1.0.1.dist-info/METADATA
mpesa_payments-1.0.1.dist-info/WHEEL
mpesa_payments-1.0.1.dist-info/top_level.txt
mpesa_payments-1.0.1.dist-info/RECORD
